google_jwt/__init__.py
google_jwt/exceptions.py
google_jwt/google_jwt.py
google_jwt-0.1.0.dist-info/WHEEL
google_jwt-0.1.0.dist-info/METADATA
google_jwt-0.1.0.dist-info/RECORD
